pushikoo_processer_re/__init__.py
pushikoo_processer_re/config.py
pushikoo_processer_re/main.py
pushikoo_processer_re-0.1.0.dist-info/METADATA
pushikoo_processer_re-0.1.0.dist-info/WHEEL
pushikoo_processer_re-0.1.0.dist-info/entry_points.txt
pushikoo_processer_re-0.1.0.dist-info/licenses/LICENSE
pushikoo_processer_re-0.1.0.dist-info/RECORD
