Metadata-Version: 2.4
Name: pushikoo-processer-re
Version: 0.1.0
Summary: A regex-based text processer for Pushikoo with configurable find/replace and terminal rules.
Project-URL: Homepage, https://github.com/Pushikoo/pushikoo-processer-re
Author: Pushikoo
License-File: LICENSE
Classifier: Operating System :: OS Independent
Classifier: Programming Language :: Python :: 3
Requires-Python: >=3.10
Requires-Dist: loguru
Requires-Dist: pushikoo-interface>=1.0.2
Provides-Extra: dev
Requires-Dist: pytest; extra == 'dev'
Requires-Dist: ruff; extra == 'dev'
